reflex_core/__init__.py
reflex_core/aws_rule.py
reflex_core/aws_rule_interface.py
reflex_core/subscription_confirmation.py
reflex_core/utilities.py
reflex_core/notifiers/__init__.py
reflex_core/notifiers/notifier.py
reflex_core/notifiers/sns_notifier.py
tests/__init__.py
tests/test_aws_rule.py
reflex_core-2.1.0.dist-info/LICENSE
reflex_core-2.1.0.dist-info/METADATA
reflex_core-2.1.0.dist-info/WHEEL
reflex_core-2.1.0.dist-info/top_level.txt
reflex_core-2.1.0.dist-info/RECORD
