Metadata-Version: 2.1
Name: reflex-core
Version: 2.1.0
Summary: Package for providing core Reflex rule classes
Home-page: https://github.com/pangolock/reflex-core
Author: Reflexive Security
Author-email: info@reflexivesecurity.com
License: UNKNOWN
Platform: UNKNOWN
Classifier: Programming Language :: Python :: 3
Classifier: License :: OSI Approved :: Mozilla Public License 2.0 (MPL 2.0)
Classifier: Operating System :: OS Independent
Requires-Python: >=3.6
Requires-Dist: boto3
Requires-Dist: requests
